
[
    {
        "route": "api/v1/acolhimento/listAll",
        "table_name": "acolhimento",
        "title": "acolhimento",
        "params": {"data": "01/05/2025 00:00:00"}
    },
    {
        "route": "api/ehr/v1/alergias/fromDate",
        "table_name": "alergias",
        "title": "alergias",
        "params": {"data": "01/05/2025 00:00:00"}
    },
    {
        "route": "api/v1/atendimento/listAll",
        "table_name": "atendimentopacientes",
        "title": "atendimentopacientes",
        "params": {"data": "01/05/2025 00:00:00"}
    },
    {
        "route": "api/v1/boletim/fromDate",
        "table_name": "boletim",
        "title": "boletim",
        "params": {"data": "01/05/2025 00:00:00", "auto_update": "True"}
    },
    {
        "route": "api/v1/classificacaorisco/listAll",
        "table_name": "classificacaorisco",
        "title": "classificacaorisco",
        "params": {"data": "01/05/2025 00:00:00"}
    },
    {
        "route": "api/v1/diagnostico/listAll",
        "table_name": "diagnostico",
        "title": "diagnostico",
        "params": {"data": "01/05/2025 00:00:00"}
    },
    {
        "route": "api/ehr/v1/episodio/fromDate",
        "table_name": "episodio",
        "title": "episodio",
        "params": {"data": "01/05/2025 00:00:00"}
    },
    {
        "route": "api/ehr/v1/exames/imagem/fromDate",
        "table_name": "exames",
        "title": "exames_imagem",
        "params": {"data": "01/05/2025 00:00:00"}
    },
    {
        "route": "api/ehr/v1/exames/laboratorio/fromDate",
        "table_name": "exames",
        "title": "exames_laboratorio",
        "params": {"data": "01/05/2025 00:00:00"}
    },
    {
        "route": "api/v1/pacientes/fromDate",
        "table_name": "pacientes",
        "title": "pacientes",
        "params": {"data": "01/05/2025 00:00:00"}
    },
    {
        "route": "api/ehr/v1/prescricaoMedicamentos/fromDate",
        "table_name": "prescricaomedicamentos",
        "title": "prescricaomedicamentos",
        "params": {"data": "01/05/2025 00:00:00"}
    },
    {
        "route": "api/ehr/v1/prescricoes/fromDate",
        "table_name": "prescricoes",
        "title": "prescricoes",
        "params": {"data": "01/05/2025 00:00:00"}
    },
    {
        "route": "api/ehr/v1/dispensacaoMedicamentos/fromDate",
        "table_name": "dispensacaomedicamentos",
        "title": "dispensacaomedicamentos",
        "params": {"data": "01/05/2025 00:00:00"}
    },
    {
        "route": "api/ehr/v1/sinaisvitais/fromDate",
        "table_name": "sinaisvitais",
        "title": "sinaisvitais",
        "params": {"data": "01/05/2025 00:00:00"}
    }
]